conversor/__init__.py
conversor/dict.py
general_conversors-1.0.8.dist-info/LICENSE
general_conversors-1.0.8.dist-info/METADATA
general_conversors-1.0.8.dist-info/WHEEL
general_conversors-1.0.8.dist-info/top_level.txt
general_conversors-1.0.8.dist-info/RECORD
