Metadata-Version: 2.1
Name: general-conversors
Version: 1.0.8
Summary: Library for convert N-level dictionaries to one-level dictionaries
Author-email: "Golden M, Inc." <software@goldenm.com>
Maintainer-email: Kenny Mochizuki <kenny@goldenm.com>
License: MIT License
Project-URL: Repository, https://github.com/goldenm-software/general-conversors
Project-URL: Changelog, https://github.com/goldenm-software/general-conversors/blob/main/CHANGELOG.md
Classifier: Programming Language :: Python :: 3
Classifier: Programming Language :: Python :: 3.8
Classifier: Programming Language :: Python :: 3.9
Classifier: Programming Language :: Python :: 3.10
Classifier: Programming Language :: Python :: 3.11
Classifier: Programming Language :: Python :: 3.12
Classifier: License :: OSI Approved :: MIT License
Requires-Python: >=3.8
License-File: LICENSE
Requires-Dist: requests
